package_name/__init__.py
ebrec-0.0.1.dist-info/LICENSE.txt
ebrec-0.0.1.dist-info/METADATA
ebrec-0.0.1.dist-info/WHEEL
ebrec-0.0.1.dist-info/top_level.txt
ebrec-0.0.1.dist-info/RECORD
