Metadata-Version: 2.1
Name: ebrec
Version: 0.0.1
Summary: A sample Python project
Author-email: "A. Random Developer" <author@example.com>
Maintainer-email: "A. Great Maintainer" <maintainer@example.com>
License: Copyright (c) 2022
Keywords: sample,setuptools,development
Classifier: Programming Language :: Python :: 3
Classifier: License :: OSI Approved :: MIT License
Classifier: Operating System :: OS Independent
Requires-Python: >=3.7
License-File: LICENSE.txt
Requires-Dist: numpy
Provides-Extra: dev
Requires-Dist: pandas ; extra == 'dev'
Provides-Extra: test
Requires-Dist: pytest ; extra == 'test'
